Mode.v
`timescale 1ns/1ps
module modeControl (
    input clock,
    input reset,
    input mode,
    input valid_vote_casted,
    input [7:0]candidate_vote0,
    input [7:0]candidate_vote1,
    input [7:0]candidate_vote2,
    input [7:0]candidate_vote3,
    input candidate_button_press0,
    input candidate_button_press1,
    input candidate_button_press2,
    input candidate_button_press3,
    output reg [7:0]led
);
  reg [30:0]counter;
  always @(posedge clock) 
  begin
   if(reset)
      counter <= 0;
   else if(valid_vote_casted)
      counter <= counter + 1;
   else if(counter != 0 & counter < 10)
      counter <= counter + 1;
   else
      counter <= 0;        
  end

  always @(posedge clock) 
  begin
    if(reset)
      led <= 0;
    else
    begin
        if(mode == 0 & counter > 0)
           led <= 8'hFF;
        else if(mode == 0)
           led <= 8'h00;
        else if(mode == 1)
        begin
            if(candidate_button_press0)
               led <= candidate_vote0;
            else if(candidate_button_press1)
               led <= candidate_vote1;
            else if(candidate_button_press2)
               led <= candidate_vote2;
            else if(candidate_button_press3)
               led <= candidate_vote3;         
        end      
    end
  end
endmodule

votelogger.v
`timescale 1ns/1ps
module voteCounter (
    input clock,
    input reset,
    input mode,
    input cand_valid_vote0,
    input cand_valid_vote1,
    input cand_valid_vote2,
    input cand_valid_vote3,
    output reg [7:0]cand_vote_recvd0,
    output reg [7:0]cand_vote_recvd1,
    output reg [7:0]cand_vote_recvd2,
    output reg [7:0]cand_vote_recvd3
);
  
  always @(posedge clock) 
  begin
    if(reset)
    begin
      cand_vote_recvd0 <= 0;
      cand_vote_recvd1 <= 0;
      cand_vote_recvd2 <= 0;
      cand_vote_recvd3 <= 0;
    end
    else
    begin
        if (cand_valid_vote0 & mode == 0) 
            cand_vote_recvd0 <= cand_vote_recvd0 + 1;
        else if(cand_valid_vote1 & mode == 0)
            cand_vote_recvd1 <= cand_vote_recvd1 + 1;
        else if(cand_valid_vote2 & mode == 0)
            cand_vote_recvd2 <= cand_vote_recvd2 + 1;
        else if(cand_valid_vote3 & mode == 0)
            cand_vote_recvd3 <= cand_vote_recvd3 + 1;            
    end
  end  
endmodule

Button.v
`timescale 1ns/1ps
module buttonControl (
    input clock,
    input reset,
    input button,
    output reg validVote 
);
  reg [30:0]counter;
  
  always @(posedge clock) 
  begin
    if (reset) 
      counter <= 0;
    else
    begin
        if (button & counter < 11) 
          counter <= counter + 1;  
        else if(!button)
          counter <= 0;
    end
  end

  always @(posedge clock) 
  begin
    if(reset)
      validVote <= 1'b0;
    else 
    begin
        if(counter == 10)
          validVote <= 1'b1;
        else
          validVote <= 1'b0;  
    end    
  end
endmodule

votingMachine.v
`timescale 1ns/1ps
`include "Button.v"
`include "Mode.v"
`include "votelogger.v"

module votingmachine (
    input clock,
    input reset,
    input mode,
    input button0,
    input button1,
    input button2,
    input button3,
    output [7:0]led
);
 wire valid_vote0;
 wire valid_vote1;
 wire valid_vote2;
 wire valid_vote3;
 wire [7:0] cand_vote_recvd0;
 wire [7:0] cand_vote_recvd1;
 wire [7:0] cand_vote_recvd2;
 wire [7:0] cand_vote_recvd3;
 wire anyvalidvote;

 assign anyvalidvote = valid_vote0|valid_vote1|valid_vote2|valid_vote3;

 buttonControl b0(.clock(clock),.reset(reset),.button(button0),.validVote(valid_vote0));    
 buttonControl b1(.clock(clock),.reset(reset),.button(button1),.validVote(valid_vote1));    
 buttonControl b2(.clock(clock),.reset(reset),.button(button2),.validVote(valid_vote2));    
 buttonControl b3(.clock(clock),.reset(reset),.button(button3),.validVote(valid_vote3));  

 voteCounter v1(
    .clock(clock),
    .reset(reset),
    .mode(mode),
    .cand_valid_vote0(valid_vote0),
    .cand_valid_vote1(valid_vote1),
    .cand_valid_vote2(valid_vote2),
    .cand_valid_vote3(valid_vote3),
    .cand_vote_recvd0(cand_vote_recvd0),
    .cand_vote_recvd1(cand_vote_recvd1),
    .cand_vote_recvd2(cand_vote_recvd2),
    .cand_vote_recvd3(cand_vote_recvd3)
);  
 
 modeControl mc(
    .clock(clock),
    .reset(reset),
    .mode(mode),
    .valid_vote_casted(anyvalidvote),
    .candidate_vote0(cand_vote_recvd0),
    .candidate_vote1(cand_vote_recvd1),
    .candidate_vote2(cand_vote_recvd2),
    .candidate_vote3(cand_vote_recvd3),
    .candidate_button_press0(valid_vote0),
    .candidate_button_press1(valid_vote1),
    .candidate_button_press2(valid_vote2),
    .candidate_button_press3(valid_vote3),
    .led(led)
);
endmodule

vm_tb.v
`timescale 1ns/1ps
`include "votingMachine.v"

module vm_tb;
    reg clock;
    reg reset;
    reg mode;
    reg Candidate1;
    reg Candidate2;
    reg Candidate3;
    reg Candidate4;
    wire [7:0]led;

    votingmachine vm(
    .clock(clock),
    .reset(reset),
    .mode(mode),
    .button0(Candidate1),
    .button1(Candidate2),
    .button2(Candidate3),
    .button3(Candidate4),
    .led(led)
    );
    
    initial begin
        clock = 0;
        forever begin
            #5 clock = ~clock;
        end
    end

    initial begin
        reset = 1;
        mode = 0;
        Candidate1 = 0;
        Candidate2 = 0;
        Candidate3 = 0;
        Candidate4 = 0;
        #100;
        #100 reset=0;mode=0;Candidate1=0;Candidate2=0;Candidate3=0;Candidate4=0;
        #5 reset=0;mode=0;Candidate1=1;Candidate2=0;Candidate3=0;Candidate4=0;
        #10 reset=0;mode=0;Candidate1=0;Candidate2=0;Candidate3=0;Candidate4=0;
        #5 reset=0;mode=0;Candidate1=1;Candidate2=0;Candidate3=0;Candidate4=0;
        #200 reset=0;mode=0;Candidate1=0;Candidate2=0;Candidate3=0;Candidate4=0;
        #5 reset=0;mode=0;Candidate1=0;Candidate2=0;Candidate3=0;Candidate4=0;
        #10 reset=0;mode=0;Candidate1=0;Candidate2=0;Candidate3=0;Candidate4=0;
        #5 reset=0;mode=0;Candidate1=0;Candidate2=0;Candidate3=0;Candidate4=0;

        #5 reset=0;mode=0;Candidate1=0;Candidate2=1;Candidate3=0;Candidate4=0;
        #200 reset=0;mode=0;Candidate1=0;Candidate2=0;Candidate3=0;Candidate4=0;
        #5 reset=0;mode=0;Candidate1=0;Candidate2=0;Candidate3=0;Candidate4=0;
        #10 reset=0;mode=0;Candidate1=0;Candidate2=0;Candidate3=0;Candidate4=0;
        #5 reset=0;mode=0;Candidate1=0;Candidate2=0;Candidate3=0;Candidate4=0;

        #5 reset=0;mode=0;Candidate1=1;Candidate2=1;Candidate3=0;Candidate4=0;
        #200 reset=0;mode=0;Candidate1=0;Candidate2=0;Candidate3=0;Candidate4=0;
        #5 reset=0;mode=0;Candidate1=0;Candidate2=0;Candidate3=0;Candidate4=0;
        #10 reset=0;mode=0;Candidate1=0;Candidate2=0;Candidate3=0;Candidate4=0;
        #5 reset=0;mode=0;Candidate1=0;Candidate2=0;Candidate3=0;Candidate4=0;

        #5 reset=0;mode=1;Candidate1=1;Candidate2=0;Candidate3=0;Candidate4=0;
        #200 reset=0;mode=0;Candidate1=0;Candidate2=0;Candidate3=0;Candidate4=0;
        #5 reset=0;mode=0;Candidate1=0;Candidate2=0;Candidate3=0;Candidate4=0;
        #10 reset=0;mode=0;Candidate1=0;Candidate2=0;Candidate3=0;Candidate4=0;
        #5 reset=0;mode=0;Candidate1=0;Candidate2=0;Candidate3=0;Candidate4=0;

        #5 reset=0;mode=1;Candidate1=0;Candidate2=1;Candidate3=0;Candidate4=0;
        #200 reset=0;mode=0;Candidate1=0;Candidate2=0;Candidate3=0;Candidate4=0;
        #5 reset=0;mode=0;Candidate1=0;Candidate2=0;Candidate3=0;Candidate4=0;
        #10 reset=0;mode=0;Candidate1=0;Candidate2=0;Candidate3=0;Candidate4=0;
        #5 reset=0;mode=0;Candidate1=0;Candidate2=0;Candidate3=0;Candidate4=0;

        #5 reset=0;mode=0;Candidate1=0;Candidate2=0;Candidate3=1;Candidate4=0;
        #200 reset=0;mode=0;Candidate1=0;Candidate2=0;Candidate3=0;Candidate4=0;
        #5 reset=0;mode=0;Candidate1=0;Candidate2=0;Candidate3=0;Candidate4=0;
        #10 reset=0;mode=0;Candidate1=0;Candidate2=0;Candidate3=0;Candidate4=0;
        #5 reset=0;mode=0;Candidate1=0;Candidate2=0;Candidate3=0;Candidate4=0;

        $finish;
    end

    initial begin
        $dumpfile("vm.vcd");
        $dumpvars(0,vm_tb);
    end

    initial
      $monitor($time,"mode = %b, Candidate1 = %b, Candidate2 = %b, Candidate3 = %b, Candidate4 = %b, led = %d",mode,Candidate1,Candidate2,Candidate3,Candidate4,led);

endmodule

vm.vcd
$date
	Sat Jul 13 20:01:28 2024
$end
$version
	Icarus Verilog
$end
$timescale
	1ps
$end
$scope module vm_tb $end
$var wire 8 ! led [7:0] $end
$var reg 1 " Candidate1 $end
$var reg 1 # Candidate2 $end
$var reg 1 $ Candidate3 $end
$var reg 1 % Candidate4 $end
$var reg 1 & clock $end
$var reg 1 ' mode $end
$var reg 1 ( reset $end
$scope module vm $end
$var wire 1 ) anyvalidvote $end
$var wire 1 " button0 $end
$var wire 1 # button1 $end
$var wire 1 $ button2 $end
$var wire 1 % button3 $end
$var wire 1 & clock $end
$var wire 1 ' mode $end
$var wire 1 ( reset $end
$var wire 1 * valid_vote3 $end
$var wire 1 + valid_vote2 $end
$var wire 1 , valid_vote1 $end
$var wire 1 - valid_vote0 $end
$var wire 8 . led [7:0] $end
$var wire 8 / cand_vote_recvd3 [7:0] $end
$var wire 8 0 cand_vote_recvd2 [7:0] $end
$var wire 8 1 cand_vote_recvd1 [7:0] $end
$var wire 8 2 cand_vote_recvd0 [7:0] $end
$scope module b0 $end
$var wire 1 " button $end
$var wire 1 & clock $end
$var wire 1 ( reset $end
$var reg 31 3 counter [30:0] $end
$var reg 1 - validVote $end
$upscope $end
$scope module b1 $end
$var wire 1 # button $end
$var wire 1 & clock $end
$var wire 1 ( reset $end
$var reg 31 4 counter [30:0] $end
$var reg 1 , validVote $end
$upscope $end
$scope module b2 $end
$var wire 1 $ button $end
$var wire 1 & clock $end
$var wire 1 ( reset $end
$var reg 31 5 counter [30:0] $end
$var reg 1 + validVote $end
$upscope $end
$scope module b3 $end
$var wire 1 % button $end
$var wire 1 & clock $end
$var wire 1 ( reset $end
$var reg 31 6 counter [30:0] $end
$var reg 1 * validVote $end
$upscope $end
$scope module mc $end
$var wire 1 - candidate_button_press0 $end
$var wire 1 , candidate_button_press1 $end
$var wire 1 + candidate_button_press2 $end
$var wire 1 * candidate_button_press3 $end
$var wire 1 & clock $end
$var wire 1 ' mode $end
$var wire 1 ( reset $end
$var wire 1 ) valid_vote_casted $end
$var wire 8 7 candidate_vote3 [7:0] $end
$var wire 8 8 candidate_vote2 [7:0] $end
$var wire 8 9 candidate_vote1 [7:0] $end
$var wire 8 : candidate_vote0 [7:0] $end
$var reg 31 ; counter [30:0] $end
$var reg 8 < led [7:0] $end
$upscope $end
$scope module v1 $end
$var wire 1 - cand_valid_vote0 $end
$var wire 1 , cand_valid_vote1 $end
$var wire 1 + cand_valid_vote2 $end
$var wire 1 * cand_valid_vote3 $end
$var wire 1 & clock $end
$var wire 1 ' mode $end
$var wire 1 ( reset $end
$var reg 8 = cand_vote_recvd0 [7:0] $end
$var reg 8 > cand_vote_recvd1 [7:0] $end
$var reg 8 ? cand_vote_recvd2 [7:0] $end
$var reg 8 @ cand_vote_recvd3 [7:0] $end
$upscope $end
$upscope $end
$upscope $end
$enddefinitions $end
#0
$dumpvars
bx @
bx ?
bx >
bx =
bx <
bx ;
bx :
bx 9
bx 8
bx 7
bx 6
bx 5
bx 4
bx 3
bx 2
bx 1
bx 0
bx /
bx .
x-
x,
x+
x*
x)
1(
0'
0&
0%
0$
0#
0"
bx !
$end
#5000
0)
b0 3
0-
b0 4
0,
b0 5
0+
b0 6
0*
b0 /
b0 7
b0 @
b0 0
b0 8
b0 ?
b0 1
b0 9
b0 >
b0 2
b0 :
b0 =
b0 ;
b0 !
b0 .
b0 <
1&
#10000
0&
#15000
1&
#20000
0&
#25000
1&
#30000
0&
#35000
1&
#40000
0&
#45000
1&
#50000
0&
#55000
1&
#60000
0&
#65000
1&
#70000
0&
#75000
1&
#80000
0&
#85000
1&
#90000
0&
#95000
1&
#100000
0&
#105000
1&
#110000
0&
#115000
1&
#120000
0&
#125000
1&
#130000
0&
#135000
1&
#140000
0&
#145000
1&
#150000
0&
#155000
1&
#160000
0&
#165000
1&
#170000
0&
#175000
1&
#180000
0&
#185000
1&
#190000
0&
#195000
1&
#200000
0&
0(
#205000
b1 3
1&
1"
#210000
0&
#215000
b0 3
1&
0"
#220000
0&
1"
#225000
b1 3
1&
#230000
0&
#235000
b10 3
1&
#240000
0&
#245000
b11 3
1&
#250000
0&
#255000
b100 3
1&
#260000
0&
#265000
b101 3
1&
#270000
0&
#275000
b110 3
1&
#280000
0&
#285000
b111 3
1&
#290000
0&
#295000
b1000 3
1&
#300000
0&
#305000
b1001 3
1&
#310000
0&
#315000
b1010 3
1&
#320000
0&
#325000
1)
b1011 3
1-
1&
#330000
0&
#335000
0)
b1 ;
b1 2
b1 :
b1 =
0-
1&
#340000
0&
#345000
b10 ;
b11111111 !
b11111111 .
b11111111 <
1&
#350000
0&
#355000
b11 ;
1&
#360000
0&
#365000
b100 ;
1&
#370000
0&
#375000
b101 ;
1&
#380000
0&
#385000
b110 ;
1&
#390000
0&
#395000
b111 ;
1&
#400000
0&
#405000
b1000 ;
1&
#410000
0&
#415000
b1001 ;
1&
#420000
0&
0"
#425000
b0 3
b1010 ;
1&
#430000
0&
#435000
b0 ;
1&
#440000
0&
#445000
b1 4
b0 !
b0 .
b0 <
1&
1#
#450000
0&
#455000
b10 4
1&
#460000
0&
#465000
b11 4
1&
#470000
0&
#475000
b100 4
1&
#480000
0&
#485000
b101 4
1&
#490000
0&
#495000
b110 4
1&
#500000
0&
#505000
b111 4
1&
#510000
0&
#515000
b1000 4
1&
#520000
0&
#525000
b1001 4
1&
#530000
0&
#535000
b1010 4
1&
#540000
0&
#545000
1)
b1011 4
1,
1&
#550000
0&
#555000
0)
b1 ;
b1 1
b1 9
b1 >
0,
1&
#560000
0&
#565000
b10 ;
b11111111 !
b11111111 .
b11111111 <
1&
#570000
0&
#575000
b11 ;
1&
#580000
0&
#585000
b100 ;
1&
#590000
0&
#595000
b101 ;
1&
#600000
0&
#605000
b110 ;
1&
#610000
0&
#615000
b111 ;
1&
#620000
0&
#625000
b1000 ;
1&
#630000
0&
#635000
b1001 ;
1&
#640000
0&
#645000
b0 4
b1010 ;
1&
0#
#650000
0&
#655000
b0 ;
1&
#660000
0&
#665000
b0 !
b0 .
b0 <
1&
#670000
0&
1#
1"
#675000
b1 4
b1 3
1&
#680000
0&
#685000
b10 3
b10 4
1&
#690000
0&
#695000
b11 4
b11 3
1&
#700000
0&
#705000
b100 3
b100 4
1&
#710000
0&
#715000
b101 4
b101 3
1&
#720000
0&
#725000
b110 3
b110 4
1&
#730000
0&
#735000
b111 4
b111 3
1&
#740000
0&
#745000
b1000 3
b1000 4
1&
#750000
0&
#755000
b1001 4
b1001 3
1&
#760000
0&
#765000
b1010 3
b1010 4
1&
#770000
0&
#775000
1)
1,
b1011 4
1-
b1011 3
1&
#780000
0&
#785000
0)
0-
0,
b10 2
b10 :
b10 =
b1 ;
1&
#790000
0&
#795000
b11111111 !
b11111111 .
b11111111 <
b10 ;
1&
#800000
0&
#805000
b11 ;
1&
#810000
0&
#815000
b100 ;
1&
#820000
0&
#825000
b101 ;
1&
#830000
0&
#835000
b110 ;
1&
#840000
0&
#845000
b111 ;
1&
#850000
0&
#855000
b1000 ;
1&
#860000
0&
#865000
b1001 ;
1&
#870000
0&
0#
0"
#875000
b1010 ;
b0 4
b0 3
1&
#880000
0&
#885000
b0 ;
1&
#890000
0&
#895000
b1 3
1&
1"
1'
#900000
0&
#905000
b10 3
1&
#910000
0&
#915000
b11 3
1&
#920000
0&
#925000
b100 3
1&
#930000
0&
#935000
b101 3
1&
#940000
0&
#945000
b110 3
1&
#950000
0&
#955000
b111 3
1&
#960000
0&
#965000
b1000 3
1&
#970000
0&
#975000
b1001 3
1&
#980000
0&
#985000
b1010 3
1&
#990000
0&
#995000
1)
1-
b1011 3
1&
#1000000
0&
#1005000
0)
0-
b1 ;
b10 !
b10 .
b10 <
1&
#1010000
0&
#1015000
b10 ;
1&
#1020000
0&
#1025000
b11 ;
1&
#1030000
0&
#1035000
b100 ;
1&
#1040000
0&
#1045000
b101 ;
1&
#1050000
0&
#1055000
b110 ;
1&
#1060000
0&
#1065000
b111 ;
1&
#1070000
0&
#1075000
b1000 ;
1&
#1080000
0&
#1085000
b1001 ;
1&
#1090000
0&
#1095000
b11111111 !
b11111111 .
b11111111 <
b1010 ;
b0 3
1&
0"
0'
#1100000
0&
#1105000
b0 ;
1&
#1110000
0&
#1115000
b0 !
b0 .
b0 <
1&
#1120000
0&
1#
1'
#1125000
b1 4
1&
#1130000
0&
#1135000
b10 4
1&
#1140000
0&
#1145000
b11 4
1&
#1150000
0&
#1155000
b100 4
1&
#1160000
0&
#1165000
b101 4
1&
#1170000
0&
#1175000
b110 4
1&
#1180000
0&
#1185000
b111 4
1&
#1190000
0&
#1195000
b1000 4
1&
#1200000
0&
#1205000
b1001 4
1&
#1210000
0&
#1215000
b1010 4
1&
#1220000
0&
#1225000
1)
b1011 4
1,
1&
#1230000
0&
#1235000
0)
b1 !
b1 .
b1 <
b1 ;
0,
1&
#1240000
0&
#1245000
b10 ;
1&
#1250000
0&
#1255000
b11 ;
1&
#1260000
0&
#1265000
b100 ;
1&
#1270000
0&
#1275000
b101 ;
1&
#1280000
0&
#1285000
b110 ;
1&
#1290000
0&
#1295000
b111 ;
1&
#1300000
0&
#1305000
b1000 ;
1&
#1310000
0&
#1315000
b1001 ;
1&
#1320000
0&
0#
0'
#1325000
b0 4
b1010 ;
b11111111 !
b11111111 .
b11111111 <
1&
#1330000
0&
#1335000
b0 ;
1&
#1340000
0&
#1345000
b1 5
b0 !
b0 .
b0 <
1&
1$
#1350000
0&
#1355000
b10 5
1&
#1360000
0&
#1365000
b11 5
1&
#1370000
0&
#1375000
b100 5
1&
#1380000
0&
#1385000
b101 5
1&
#1390000
0&
#1395000
b110 5
1&
#1400000
0&
#1405000
b111 5
1&
#1410000
0&
#1415000
b1000 5
1&
#1420000
0&
#1425000
b1001 5
1&
#1430000
0&
#1435000
b1010 5
1&
#1440000
0&
#1445000
1)
b1011 5
1+
1&
#1450000
0&
#1455000
0)
b1 ;
b1 0
b1 8
b1 ?
0+
1&
#1460000
0&
#1465000
b10 ;
b11111111 !
b11111111 .
b11111111 <
1&
#1470000
0&
#1475000
b11 ;
1&
#1480000
0&
#1485000
b100 ;
1&
#1490000
0&
#1495000
b101 ;
1&
#1500000
0&
#1505000
b110 ;
1&
#1510000
0&
#1515000
b111 ;
1&
#1520000
0&
#1525000
b1000 ;
1&
#1530000
0&
#1535000
b1001 ;
1&
#1540000
0&
#1545000
b0 5
b1010 ;
1&
0$
#1550000
0&
#1555000
b0 ;
1&
#1560000
0&
#1565000
b0 !
b0 .
b0 <
1&
